{
  "resourceType": "ImplementationGuide",
  "id": "hl7.be.core",
  "text": {
    "status": "generated",
    "div": "<div xmlns=\"http://www.w3.org/1999/xhtml\"><h2>BaseIG</h2><p>The official URL for this implementation guide is: </p><pre>https://www.ehealth.fgov.be/standards/fhir/ImplementationGuide/hl7.be.core</pre><div><p>The Core Belgian Profiles provide the essential and common requirement for FHIR implementations in Belgium</p>\n</div></div>"
  },
  "url": "https://www.ehealth.fgov.be/standards/fhir/ImplementationGuide/hl7.be.core",
  "version": "0.1.0",
  "name": "BaseIG",
  "title": "FHIR Belgium Base IG",
  "status": "draft",
  "experimental": false,
  "date": "2020-01-30T20:40:02+01:00",
  "publisher": "HL7 Belgium",
  "contact": [
    {
      "telecom": [
        {
          "system": "other",
          "value": "http://hl7.org/Special/committees/fiwg"
        }
      ]
    }
  ],
  "description": "The Core Belgian Profiles provide the essential and common requirement for FHIR implementations in Belgium",
  "jurisdiction": [
    {
      "coding": [
        {
          "system": "http://unstats.un.org/unsd/methods/m49/m49.htm",
          "code": "056"
        }
      ],
      "text": "Belgium"
    }
  ],
  "packageId": "hl7.be.core",
  "license": "CC0-1.0",
  "fhirVersion": [
    "4.0.1"
  ],
  "definition": {
    "extension": [
      {
        "extension": [
          {
            "url": "code",
            "valueString": "active-tables"
          },
          {
            "url": "value",
            "valueString": "true"
          }
        ],
        "url": "http://hl7.org/fhir/tools/StructureDefinition/ig-parameter"
      },
      {
        "extension": [
          {
            "url": "code",
            "valueString": "copyrightyear"
          },
          {
            "url": "value",
            "valueString": "2020"
          }
        ],
        "url": "http://hl7.org/fhir/tools/StructureDefinition/ig-parameter"
      },
      {
        "extension": [
          {
            "url": "code",
            "valueString": "releaselabel"
          },
          {
            "url": "value",
            "valueString": "CI build"
          }
        ],
        "url": "http://hl7.org/fhir/tools/StructureDefinition/ig-parameter"
      },
      {
        "extension": [
          {
            "url": "code",
            "valueString": "autoload-resources"
          },
          {
            "url": "value",
            "valueString": "true"
          }
        ],
        "url": "http://hl7.org/fhir/tools/StructureDefinition/ig-parameter"
      },
      {
        "extension": [
          {
            "url": "code",
            "valueString": "path-qa"
          },
          {
            "url": "value",
            "valueString": "temp/qa"
          }
        ],
        "url": "http://hl7.org/fhir/tools/StructureDefinition/ig-parameter"
      },
      {
        "extension": [
          {
            "url": "code",
            "valueString": "path-temp"
          },
          {
            "url": "value",
            "valueString": "temp/pages"
          }
        ],
        "url": "http://hl7.org/fhir/tools/StructureDefinition/ig-parameter"
      },
      {
        "extension": [
          {
            "url": "code",
            "valueString": "path-output"
          },
          {
            "url": "value",
            "valueString": "output"
          }
        ],
        "url": "http://hl7.org/fhir/tools/StructureDefinition/ig-parameter"
      },
      {
        "extension": [
          {
            "url": "code",
            "valueString": "path-suppressed-warnings"
          },
          {
            "url": "value",
            "valueString": "input/ignoreWarnings.txt"
          }
        ],
        "url": "http://hl7.org/fhir/tools/StructureDefinition/ig-parameter"
      },
      {
        "extension": [
          {
            "url": "code",
            "valueString": "template-html"
          },
          {
            "url": "value",
            "valueString": "template-page.html"
          }
        ],
        "url": "http://hl7.org/fhir/tools/StructureDefinition/ig-parameter"
      },
      {
        "extension": [
          {
            "url": "code",
            "valueString": "template-md"
          },
          {
            "url": "value",
            "valueString": "template-page-md.html"
          }
        ],
        "url": "http://hl7.org/fhir/tools/StructureDefinition/ig-parameter"
      },
      {
        "extension": [
          {
            "url": "code",
            "valueString": "apply-contact"
          },
          {
            "url": "value",
            "valueString": "true"
          }
        ],
        "url": "http://hl7.org/fhir/tools/StructureDefinition/ig-parameter"
      },
      {
        "extension": [
          {
            "url": "code",
            "valueString": "apply-context"
          },
          {
            "url": "value",
            "valueString": "true"
          }
        ],
        "url": "http://hl7.org/fhir/tools/StructureDefinition/ig-parameter"
      },
      {
        "extension": [
          {
            "url": "code",
            "valueString": "apply-copyright"
          },
          {
            "url": "value",
            "valueString": "true"
          }
        ],
        "url": "http://hl7.org/fhir/tools/StructureDefinition/ig-parameter"
      },
      {
        "extension": [
          {
            "url": "code",
            "valueString": "apply-jurisdiction"
          },
          {
            "url": "value",
            "valueString": "true"
          }
        ],
        "url": "http://hl7.org/fhir/tools/StructureDefinition/ig-parameter"
      },
      {
        "extension": [
          {
            "url": "code",
            "valueString": "apply-license"
          },
          {
            "url": "value",
            "valueString": "true"
          }
        ],
        "url": "http://hl7.org/fhir/tools/StructureDefinition/ig-parameter"
      },
      {
        "extension": [
          {
            "url": "code",
            "valueString": "apply-publisher"
          },
          {
            "url": "value",
            "valueString": "true"
          }
        ],
        "url": "http://hl7.org/fhir/tools/StructureDefinition/ig-parameter"
      },
      {
        "extension": [
          {
            "url": "code",
            "valueString": "apply-version"
          },
          {
            "url": "value",
            "valueString": "true"
          }
        ],
        "url": "http://hl7.org/fhir/tools/StructureDefinition/ig-parameter"
      }
    ],
    "grouping": [
      {
        "id": "logicalmodels",
        "name": "Logical Models",
        "description": "The common Belgian Logical Models - these can be mapped to KMEHR and FHIR"
      },
      {
        "id": "datatypes",
        "name": "Data Types",
        "description": "Specific Belgian data types"
      },
      {
        "id": "core",
        "name": "Core Profiles",
        "description": "Core resources to be reused in other resources"
      },
      {
        "name": "Conditions",
        "description": "Conditions and findings about patients"
      },
      {
        "id": "communication",
        "name": "Communication",
        "description": "Communication and Care Coordination"
      },
      {
        "id": "condition",
        "name": "Conditions",
        "description": "Resource profiles defined for conditions"
      },
      {
        "id": "medication",
        "name": "Medication",
        "description": "Resource profiles defined for medication"
      },
      {
        "id": "documents",
        "name": "Documents",
        "description": "Documents curated extracts of information - they represent a set of information for a given context at a given time."
      },
      {
        "id": "terminology",
        "name": "Terminology",
        "description": "Terminology resources - ValueSets and CodeSystems"
      },
      {
        "id": "examples",
        "name": "Examples",
        "description": "Example resources"
      }
    ],
    "resource": [
      {
        "extension": [
          {
            "url": "http://hl7.org/fhir/tools/StructureDefinition/resource-information",
            "valueString": "StructureDefinition:resource"
          },
          {
            "url": "http://hl7.org/fhir/StructureDefinition/implementationguide-page",
            "valueUri": "StructureDefinition-be-communication.html"
          }
        ],
        "reference": {
          "reference": "StructureDefinition/be-communication"
        },
        "fhirVersion": [
          "4.0.1"
        ],
        "name": "Communication Profile",
        "description": "Communication / Diary Note profile",
        "groupingId": "communication"
      },
      {
        "extension": [
          {
            "url": "http://hl7.org/fhir/tools/StructureDefinition/resource-information",
            "valueString": "StructureDefinition:resource"
          },
          {
            "url": "http://hl7.org/fhir/StructureDefinition/implementationguide-page",
            "valueUri": "StructureDefinition-be-careplan.html"
          }
        ],
        "reference": {
          "reference": "StructureDefinition/be-careplan"
        },
        "fhirVersion": [
          "4.0.1"
        ],
        "name": "Care Plan profile",
        "description": "Care Plan profile",
        "groupingId": "communication"
      },
      {
        "extension": [
          {
            "url": "http://hl7.org/fhir/tools/StructureDefinition/resource-information",
            "valueString": "StructureDefinition:resource"
          },
          {
            "url": "http://hl7.org/fhir/StructureDefinition/implementationguide-page",
            "valueUri": "StructureDefinition-be-careteam.html"
          }
        ],
        "reference": {
          "reference": "StructureDefinition/be-careteam"
        },
        "fhirVersion": [
          "4.0.1"
        ],
        "name": "Care Team profile",
        "description": "This is the Belgian profile for Care Plan. A Care Plan contains the activities planned and/or performed by a care team to deliver care for a particular patient, usually targeting a specific condition or set of conditions.",
        "groupingId": "communication"
      },
      {
        "extension": [
          {
            "url": "http://hl7.org/fhir/tools/StructureDefinition/resource-information",
            "valueString": "StructureDefinition:resource"
          },
          {
            "url": "http://hl7.org/fhir/StructureDefinition/implementationguide-page",
            "valueUri": "StructureDefinition-be-patient.html"
          }
        ],
        "reference": {
          "reference": "StructureDefinition/be-patient"
        },
        "fhirVersion": [
          "4.0.1"
        ],
        "name": "BE Patient profile",
        "description": "Core Belgian Patient profile",
        "groupingId": "core"
      },
      {
        "extension": [
          {
            "url": "http://hl7.org/fhir/tools/StructureDefinition/resource-information",
            "valueString": "StructureDefinition:resource"
          },
          {
            "url": "http://hl7.org/fhir/StructureDefinition/implementationguide-page",
            "valueUri": "StructureDefinition-be-practitionerrole.html"
          }
        ],
        "reference": {
          "reference": "StructureDefinition/be-practitionerrole"
        },
        "fhirVersion": [
          "4.0.1"
        ],
        "name": "BE Practitioner Role profile",
        "description": "Core Belgian Practitioner Role profile",
        "groupingId": "core"
      },
      {
        "extension": [
          {
            "url": "http://hl7.org/fhir/tools/StructureDefinition/resource-information",
            "valueString": "StructureDefinition:complex-type"
          },
          {
            "url": "http://hl7.org/fhir/StructureDefinition/implementationguide-page",
            "valueUri": "StructureDefinition-be-address.html"
          }
        ],
        "reference": {
          "reference": "StructureDefinition/be-address"
        },
        "fhirVersion": [
          "4.0.1"
        ],
        "name": "Belgian Address",
        "description": "Belgian Address",
        "groupingId": "datatypes"
      },
      {
        "extension": [
          {
            "url": "http://hl7.org/fhir/tools/StructureDefinition/resource-information",
            "valueString": "StructureDefinition:primitive-type"
          },
          {
            "url": "http://hl7.org/fhir/StructureDefinition/implementationguide-page",
            "valueUri": "StructureDefinition-string320.html"
          }
        ],
        "reference": {
          "reference": "StructureDefinition/string320"
        },
        "fhirVersion": [
          "4.0.1"
        ],
        "name": "String wih max 320 characters",
        "description": "String wih max 320 characters",
        "groupingId": "datatypes"
      },
      {
        "extension": [
          {
            "url": "http://hl7.org/fhir/tools/StructureDefinition/resource-information",
            "valueString": "StructureDefinition:resource"
          },
          {
            "url": "http://hl7.org/fhir/StructureDefinition/implementationguide-page",
            "valueUri": "StructureDefinition-be-practitioner.html"
          }
        ],
        "reference": {
          "reference": "StructureDefinition/be-practitioner"
        },
        "fhirVersion": [
          "4.0.1"
        ],
        "name": "BE Practitioner profile",
        "description": "Core Belgian Practitioner profile",
        "groupingId": "core"
      },
      {
        "extension": [
          {
            "url": "http://hl7.org/fhir/tools/StructureDefinition/resource-information",
            "valueString": "StructureDefinition:logical"
          },
          {
            "url": "http://hl7.org/fhir/StructureDefinition/implementationguide-page",
            "valueUri": "StructureDefinition-be-careteam-model.html"
          }
        ],
        "reference": {
          "reference": "StructureDefinition/be-careteam-model"
        },
        "fhirVersion": [
          "4.0.1"
        ],
        "name": "Logical Model Care Team",
        "description": "Care Team logical model",
        "groupingId": "logicalmodels"
      },
      {
        "extension": [
          {
            "url": "http://hl7.org/fhir/tools/StructureDefinition/resource-information",
            "valueString": "StructureDefinition:logical"
          },
          {
            "url": "http://hl7.org/fhir/StructureDefinition/implementationguide-page",
            "valueUri": "StructureDefinition-lm-be-communication.html"
          }
        ],
        "reference": {
          "reference": "StructureDefinition/lm-be-communication"
        },
        "fhirVersion": [
          "4.0.1"
        ],
        "name": "Logical Model Communication",
        "description": "Communication / Diary Note logical model",
        "groupingId": "logicalmodels"
      },
      {
        "extension": [
          {
            "url": "http://hl7.org/fhir/tools/StructureDefinition/resource-information",
            "valueString": "CapabilityStatement"
          },
          {
            "url": "http://hl7.org/fhir/StructureDefinition/implementationguide-page",
            "valueUri": "CapabilityStatement-be-communicationclient.html"
          }
        ],
        "reference": {
          "reference": "CapabilityStatement/be-communicationclient"
        },
        "fhirVersion": [
          "4.0.1"
        ],
        "name": "Communication Apps",
        "groupingId": "core"
      },
      {
        "extension": [
          {
            "url": "http://hl7.org/fhir/tools/StructureDefinition/resource-information",
            "valueString": "CapabilityStatement"
          },
          {
            "url": "http://hl7.org/fhir/StructureDefinition/implementationguide-page",
            "valueUri": "CapabilityStatement-be-communicationserver.html"
          }
        ],
        "reference": {
          "reference": "CapabilityStatement/be-communicationserver"
        },
        "fhirVersion": [
          "4.0.1"
        ],
        "name": "Communication Server",
        "groupingId": "core"
      },
      {
        "extension": [
          {
            "url": "http://hl7.org/fhir/tools/StructureDefinition/resource-information",
            "valueString": "ValueSet"
          },
          {
            "url": "http://hl7.org/fhir/StructureDefinition/implementationguide-page",
            "valueUri": "ValueSet-be-diarytopic.html"
          }
        ],
        "reference": {
          "reference": "ValueSet/be-diarytopic"
        },
        "fhirVersion": [
          "4.0.1"
        ],
        "name": "ValueSet - CommunicationTopic",
        "description": "The values for communication topic",
        "groupingId": "terminology"
      },
      {
        "extension": [
          {
            "url": "http://hl7.org/fhir/tools/StructureDefinition/resource-information",
            "valueString": "CodeSystem"
          },
          {
            "url": "http://hl7.org/fhir/StructureDefinition/implementationguide-page",
            "valueUri": "CodeSystem-be-diarytopic.html"
          }
        ],
        "reference": {
          "reference": "CodeSystem/be-diarytopic"
        },
        "fhirVersion": [
          "4.0.1"
        ],
        "name": "CodeSystem - CommunicationTopic",
        "description": "The values for communication topic",
        "groupingId": "terminology"
      },
      {
        "extension": [
          {
            "url": "http://hl7.org/fhir/tools/StructureDefinition/resource-information",
            "valueString": "StructureDefinition:resource"
          },
          {
            "url": "http://hl7.org/fhir/StructureDefinition/implementationguide-page",
            "valueUri": "StructureDefinition-be-allergyintolerance.html"
          }
        ],
        "reference": {
          "reference": "StructureDefinition/be-allergyintolerance"
        },
        "fhirVersion": [
          "4.0.1"
        ],
        "name": "Allergy Intolerance core BE profile",
        "description": "The Core BE profile for Allergy Intolerance",
        "groupingId": "condition"
      },
      {
        "extension": [
          {
            "url": "http://hl7.org/fhir/tools/StructureDefinition/resource-information",
            "valueString": "ValueSet"
          },
          {
            "url": "http://hl7.org/fhir/StructureDefinition/implementationguide-page",
            "valueUri": "ValueSet-be-contactperson.html"
          }
        ],
        "reference": {
          "reference": "ValueSet/be-contactperson"
        },
        "fhirVersion": [
          "4.0.1"
        ],
        "name": "ValueSet - Contact Person",
        "description": "The values for Contact Person type",
        "groupingId": "terminology"
      },
      {
        "extension": [
          {
            "url": "http://hl7.org/fhir/tools/StructureDefinition/resource-information",
            "valueString": "CodeSystem"
          },
          {
            "url": "http://hl7.org/fhir/StructureDefinition/implementationguide-page",
            "valueUri": "CodeSystem-be-contactperson.html"
          }
        ],
        "reference": {
          "reference": "CodeSystem/be-contactperson"
        },
        "fhirVersion": [
          "4.0.1"
        ],
        "name": "CodeSystem - Contact Person",
        "description": "The values for Contact Person type",
        "groupingId": "terminology"
      },
      {
        "extension": [
          {
            "url": "http://hl7.org/fhir/tools/StructureDefinition/resource-information",
            "valueString": "ValueSet"
          },
          {
            "url": "http://hl7.org/fhir/StructureDefinition/implementationguide-page",
            "valueUri": "ValueSet-be-causativeagent.html"
          }
        ],
        "reference": {
          "reference": "ValueSet/be-causativeagent"
        },
        "fhirVersion": [
          "4.0.1"
        ],
        "name": "ValueSet - Causative Agent",
        "description": "The list of causative agents",
        "groupingId": "terminology"
      },
      {
        "extension": [
          {
            "url": "http://hl7.org/fhir/tools/StructureDefinition/resource-information",
            "valueString": "ValueSet"
          },
          {
            "url": "http://hl7.org/fhir/StructureDefinition/implementationguide-page",
            "valueUri": "ValueSet-be-riskmanifestation.html"
          }
        ],
        "reference": {
          "reference": "ValueSet/be-riskmanifestation"
        },
        "fhirVersion": [
          "4.0.1"
        ],
        "name": "ValueSet - Risk Manifestation",
        "description": "The values for Risk Manifestation",
        "groupingId": "terminology"
      },
      {
        "extension": [
          {
            "url": "http://hl7.org/fhir/tools/StructureDefinition/resource-information",
            "valueString": "ValueSet"
          },
          {
            "url": "http://hl7.org/fhir/StructureDefinition/implementationguide-page",
            "valueUri": "ValueSet-be-civilstate.html"
          }
        ],
        "reference": {
          "reference": "ValueSet/be-civilstate"
        },
        "fhirVersion": [
          "4.0.1"
        ],
        "name": "ValueSet - Civil State",
        "description": "The values for Civil State",
        "groupingId": "terminology"
      },
      {
        "extension": [
          {
            "url": "http://hl7.org/fhir/tools/StructureDefinition/resource-information",
            "valueString": "CodeSystem"
          },
          {
            "url": "http://hl7.org/fhir/StructureDefinition/implementationguide-page",
            "valueUri": "CodeSystem-be-civilstate.html"
          }
        ],
        "reference": {
          "reference": "CodeSystem/be-civilstate"
        },
        "fhirVersion": [
          "4.0.1"
        ],
        "name": "CodeSystem - Civil State",
        "description": "The official values for Civil State",
        "groupingId": "terminology"
      },
      {
        "extension": [
          {
            "url": "http://hl7.org/fhir/tools/StructureDefinition/resource-information",
            "valueString": "CodeSystem"
          },
          {
            "url": "http://hl7.org/fhir/StructureDefinition/implementationguide-page",
            "valueUri": "CodeSystem-be-hcparty.html"
          }
        ],
        "reference": {
          "reference": "CodeSystem/be-hcparty"
        },
        "fhirVersion": [
          "4.0.1"
        ],
        "name": "CodeSystem - Healthcare Party",
        "description": "The values for healthcare party types",
        "groupingId": "terminology"
      },
      {
        "extension": [
          {
            "url": "http://hl7.org/fhir/tools/StructureDefinition/resource-information",
            "valueString": "Communication"
          },
          {
            "url": "http://hl7.org/fhir/StructureDefinition/implementationguide-page",
            "valueUri": "Communication-be.comm1.html"
          }
        ],
        "reference": {
          "reference": "Communication/be.comm1"
        },
        "fhirVersion": [
          "4.0.1"
        ],
        "name": "Communication example 1",
        "description": "New message from DZOP to nurse",
        "exampleCanonical": "https://www.ehealth.fgov.be/standards/fhir/StructureDefinition/be-communication",
        "groupingId": "examples"
      },
      {
        "extension": [
          {
            "url": "http://hl7.org/fhir/tools/StructureDefinition/resource-information",
            "valueString": "Patient"
          },
          {
            "url": "http://hl7.org/fhir/StructureDefinition/implementationguide-page",
            "valueUri": "Patient-pia.html"
          }
        ],
        "reference": {
          "reference": "Patient/pia"
        },
        "fhirVersion": [
          "4.0.1"
        ],
        "name": "Patient Pia",
        "description": "Patient Pia",
        "exampleBoolean": true
      },
      {
        "extension": [
          {
            "url": "http://hl7.org/fhir/tools/StructureDefinition/resource-information",
            "valueString": "Practitioner"
          },
          {
            "url": "http://hl7.org/fhir/StructureDefinition/implementationguide-page",
            "valueUri": "Practitioner-dragon.html"
          }
        ],
        "reference": {
          "reference": "Practitioner/dragon"
        },
        "fhirVersion": [
          "4.0.1"
        ],
        "name": "Dr. Dragon",
        "description": "Dr. Dragon",
        "exampleBoolean": true
      },
      {
        "extension": [
          {
            "url": "http://hl7.org/fhir/tools/StructureDefinition/resource-information",
            "valueString": "Communication"
          },
          {
            "url": "http://hl7.org/fhir/StructureDefinition/implementationguide-page",
            "valueUri": "Communication-be.comm2.1.html"
          }
        ],
        "reference": {
          "reference": "Communication/be.comm2.1"
        },
        "fhirVersion": [
          "4.0.1"
        ],
        "name": "Communication example 2",
        "description": "Long message - part 1",
        "exampleCanonical": "https://www.ehealth.fgov.be/standards/fhir/StructureDefinition/be-communication",
        "groupingId": "examples"
      },
      {
        "extension": [
          {
            "url": "http://hl7.org/fhir/tools/StructureDefinition/resource-information",
            "valueString": "Communication"
          },
          {
            "url": "http://hl7.org/fhir/StructureDefinition/implementationguide-page",
            "valueUri": "Communication-be.comm2.2.html"
          }
        ],
        "reference": {
          "reference": "Communication/be.comm2.2"
        },
        "fhirVersion": [
          "4.0.1"
        ],
        "name": "Communication example 3",
        "description": "Long message - part 2",
        "exampleCanonical": "https://www.ehealth.fgov.be/standards/fhir/StructureDefinition/be-communication",
        "groupingId": "examples"
      },
      {
        "extension": [
          {
            "url": "http://hl7.org/fhir/tools/StructureDefinition/resource-information",
            "valueString": "Communication"
          },
          {
            "url": "http://hl7.org/fhir/StructureDefinition/implementationguide-page",
            "valueUri": "Communication-be.comm2.3.html"
          }
        ],
        "reference": {
          "reference": "Communication/be.comm2.3"
        },
        "fhirVersion": [
          "4.0.1"
        ],
        "name": "Communication example 4",
        "description": "Long message - part 3",
        "exampleCanonical": "https://www.ehealth.fgov.be/standards/fhir/StructureDefinition/be-communication",
        "groupingId": "examples"
      },
      {
        "extension": [
          {
            "url": "http://hl7.org/fhir/tools/StructureDefinition/resource-information",
            "valueString": "Communication"
          },
          {
            "url": "http://hl7.org/fhir/StructureDefinition/implementationguide-page",
            "valueUri": "Communication-be.comm3.1.html"
          }
        ],
        "reference": {
          "reference": "Communication/be.comm3.1"
        },
        "fhirVersion": [
          "4.0.1"
        ],
        "name": "Communication example 5",
        "description": "Send notice / question",
        "exampleCanonical": "https://www.ehealth.fgov.be/standards/fhir/StructureDefinition/be-communication",
        "groupingId": "examples"
      },
      {
        "extension": [
          {
            "url": "http://hl7.org/fhir/tools/StructureDefinition/resource-information",
            "valueString": "Communication"
          },
          {
            "url": "http://hl7.org/fhir/StructureDefinition/implementationguide-page",
            "valueUri": "Communication-be.comm3.2.html"
          }
        ],
        "reference": {
          "reference": "Communication/be.comm3.2"
        },
        "fhirVersion": [
          "4.0.1"
        ],
        "name": "Communication example 6",
        "description": "Reply to question",
        "exampleCanonical": "https://www.ehealth.fgov.be/standards/fhir/StructureDefinition/be-communication",
        "groupingId": "examples"
      },
      {
        "extension": [
          {
            "url": "http://hl7.org/fhir/tools/StructureDefinition/resource-information",
            "valueString": "Communication"
          },
          {
            "url": "http://hl7.org/fhir/StructureDefinition/implementationguide-page",
            "valueUri": "Communication-be.comm4.1.html"
          }
        ],
        "reference": {
          "reference": "Communication/be.comm4.1"
        },
        "fhirVersion": [
          "4.0.1"
        ],
        "name": "Communication example 7",
        "description": "Send notification",
        "exampleCanonical": "https://www.ehealth.fgov.be/standards/fhir/StructureDefinition/be-communication",
        "groupingId": "examples"
      },
      {
        "extension": [
          {
            "url": "http://hl7.org/fhir/tools/StructureDefinition/resource-information",
            "valueString": "Communication"
          },
          {
            "url": "http://hl7.org/fhir/StructureDefinition/implementationguide-page",
            "valueUri": "Communication-be.comm4.2.html"
          }
        ],
        "reference": {
          "reference": "Communication/be.comm4.2"
        },
        "fhirVersion": [
          "4.0.1"
        ],
        "name": "Communication example 8",
        "description": "Send reminder",
        "exampleCanonical": "https://www.ehealth.fgov.be/standards/fhir/StructureDefinition/be-communication",
        "groupingId": "examples"
      },
      {
        "extension": [
          {
            "url": "http://hl7.org/fhir/tools/StructureDefinition/resource-information",
            "valueString": "Communication"
          },
          {
            "url": "http://hl7.org/fhir/StructureDefinition/implementationguide-page",
            "valueUri": "Communication-be.comm5.1.html"
          }
        ],
        "reference": {
          "reference": "Communication/be.comm5.1"
        },
        "fhirVersion": [
          "4.0.1"
        ],
        "name": "Communication example 9",
        "description": "Send attachment",
        "exampleCanonical": "https://www.ehealth.fgov.be/standards/fhir/StructureDefinition/be-communication",
        "groupingId": "examples"
      },
      {
        "extension": [
          {
            "url": "http://hl7.org/fhir/tools/StructureDefinition/resource-information",
            "valueString": "Communication"
          },
          {
            "url": "http://hl7.org/fhir/StructureDefinition/implementationguide-page",
            "valueUri": "Communication-be.comm5.2.html"
          }
        ],
        "reference": {
          "reference": "Communication/be.comm5.2"
        },
        "fhirVersion": [
          "4.0.1"
        ],
        "name": "Communication example 10",
        "description": "Forward existing attachment",
        "exampleCanonical": "https://www.ehealth.fgov.be/standards/fhir/StructureDefinition/be-communication",
        "groupingId": "examples"
      },
      {
        "extension": [
          {
            "url": "http://hl7.org/fhir/tools/StructureDefinition/resource-information",
            "valueString": "Communication"
          },
          {
            "url": "http://hl7.org/fhir/StructureDefinition/implementationguide-page",
            "valueUri": "Communication-be.comm6.html"
          }
        ],
        "reference": {
          "reference": "Communication/be.comm6"
        },
        "fhirVersion": [
          "4.0.1"
        ],
        "name": "Communication example 11",
        "description": "High-priority notification",
        "exampleCanonical": "https://www.ehealth.fgov.be/standards/fhir/StructureDefinition/be-communication",
        "groupingId": "examples"
      },
      {
        "extension": [
          {
            "url": "http://hl7.org/fhir/tools/StructureDefinition/resource-information",
            "valueString": "CareTeam"
          },
          {
            "url": "http://hl7.org/fhir/StructureDefinition/implementationguide-page",
            "valueUri": "CareTeam-dzop-team-0002.html"
          }
        ],
        "reference": {
          "reference": "CareTeam/dzop-team-0002"
        },
        "fhirVersion": [
          "4.0.1"
        ],
        "name": "Care Team Pia",
        "description": "The Care Team responsible for Pia's care",
        "exampleCanonical": "https://www.ehealth.fgov.be/standards/fhir/StructureDefinition/be-careteam",
        "groupingId": "examples"
      },
      {
        "extension": [
          {
            "url": "http://hl7.org/fhir/tools/StructureDefinition/resource-information",
            "valueString": "Condition"
          },
          {
            "url": "http://hl7.org/fhir/StructureDefinition/implementationguide-page",
            "valueUri": "Condition-pia-diabetes.html"
          }
        ],
        "reference": {
          "reference": "Condition/pia-diabetes"
        },
        "fhirVersion": [
          "4.0.1"
        ],
        "name": "Condition - Pia diabetes",
        "description": "Patient Pia has diabetes",
        "groupingId": "examples"
      },
      {
        "extension": [
          {
            "url": "http://hl7.org/fhir/tools/StructureDefinition/resource-information",
            "valueString": "Condition"
          },
          {
            "url": "http://hl7.org/fhir/StructureDefinition/implementationguide-page",
            "valueUri": "Condition-pia-loneliness.html"
          }
        ],
        "reference": {
          "reference": "Condition/pia-loneliness"
        },
        "fhirVersion": [
          "4.0.1"
        ],
        "name": "Condition - Pia loneliness",
        "description": "Patient Pia feels lonely",
        "groupingId": "examples"
      },
      {
        "extension": [
          {
            "url": "http://hl7.org/fhir/tools/StructureDefinition/resource-information",
            "valueString": "Condition"
          },
          {
            "url": "http://hl7.org/fhir/StructureDefinition/implementationguide-page",
            "valueUri": "Condition-pia-postop.html"
          }
        ],
        "reference": {
          "reference": "Condition/pia-postop"
        },
        "fhirVersion": [
          "4.0.1"
        ],
        "name": "Condition - Pia's surgery recovery",
        "description": "Patient Pia had a surgery and needs to recover",
        "groupingId": "examples"
      },
      {
        "extension": [
          {
            "url": "http://hl7.org/fhir/tools/StructureDefinition/resource-information",
            "valueString": "Condition"
          },
          {
            "url": "http://hl7.org/fhir/StructureDefinition/implementationguide-page",
            "valueUri": "Condition-pia-depression.html"
          }
        ],
        "reference": {
          "reference": "Condition/pia-depression"
        },
        "fhirVersion": [
          "4.0.1"
        ],
        "name": "Condition - Pia depression",
        "description": "Patient Pia has a depression",
        "groupingId": "examples"
      },
      {
        "extension": [
          {
            "url": "http://hl7.org/fhir/tools/StructureDefinition/resource-information",
            "valueString": "Patient"
          },
          {
            "url": "http://hl7.org/fhir/StructureDefinition/implementationguide-page",
            "valueUri": "Patient-peter.html"
          }
        ],
        "reference": {
          "reference": "Patient/peter"
        },
        "name": "Example Patient - peter",
        "exampleCanonical": "https://www.ehealth.fgov.be/standards/fhir/StructureDefinition/be-patient"
      },
      {
        "extension": [
          {
            "url": "http://hl7.org/fhir/tools/StructureDefinition/resource-information",
            "valueString": "StructureDefinition:extension"
          },
          {
            "url": "http://hl7.org/fhir/StructureDefinition/implementationguide-page",
            "valueUri": "StructureDefinition-language.html"
          }
        ],
        "reference": {
          "reference": "StructureDefinition/language"
        },
        "name": "Human Language of the item",
        "description": "The Human Language of the item."
      },
      {
        "extension": [
          {
            "url": "http://hl7.org/fhir/tools/StructureDefinition/resource-information",
            "valueString": "StructureDefinition:extension"
          },
          {
            "url": "http://hl7.org/fhir/StructureDefinition/implementationguide-page",
            "valueUri": "StructureDefinition-patient-birthPlace.html"
          }
        ],
        "reference": {
          "reference": "StructureDefinition/patient-birthPlace"
        },
        "name": "Birth Place",
        "description": "The registered place of birth of the patient. A sytem may use the address.text if they don't store the birthPlace address in discrete elements."
      },
      {
        "extension": [
          {
            "url": "http://hl7.org/fhir/tools/StructureDefinition/resource-information",
            "valueString": "StructureDefinition:extension"
          },
          {
            "url": "http://hl7.org/fhir/StructureDefinition/implementationguide-page",
            "valueUri": "StructureDefinition-patient-birthTime.html"
          }
        ],
        "reference": {
          "reference": "StructureDefinition/patient-birthTime"
        },
        "name": "Birth Time",
        "description": "The time of day that the Patient was born. This includes the date to ensure that the timezone information can be communicated effectively."
      },
      {
        "extension": [
          {
            "url": "http://hl7.org/fhir/tools/StructureDefinition/resource-information",
            "valueString": "StructureDefinition:extension"
          },
          {
            "url": "http://hl7.org/fhir/StructureDefinition/implementationguide-page",
            "valueUri": "StructureDefinition-patient-nationality.html"
          }
        ],
        "reference": {
          "reference": "StructureDefinition/patient-nationality"
        },
        "name": "nationality",
        "description": "The nationality of the patient."
      },
      {
        "extension": [
          {
            "url": "http://hl7.org/fhir/tools/StructureDefinition/resource-information",
            "valueString": "StructureDefinition:resource"
          },
          {
            "url": "http://hl7.org/fhir/StructureDefinition/implementationguide-page",
            "valueUri": "StructureDefinition-be-medicationtreatment.html"
          }
        ],
        "reference": {
          "reference": "StructureDefinition/be-medicationtreatment"
        }
      }
    ],
    "page": {
      "nameUrl": "toc.html",
      "title": "Table of Contents",
      "generation": "html",
      "page": [
        {
          "nameUrl": "index.html",
          "title": "BE Core Home Page",
          "generation": "html"
        },
        {
          "nameUrl": "conventions.html",
          "title": "Conventions",
          "generation": "markdown"
        },
        {
          "nameUrl": "functional-overview.html",
          "title": "Functional Description",
          "generation": "markdown"
        },
        {
          "nameUrl": "logical-models.html",
          "title": "Logical Data Models",
          "generation": "markdown"
        },
        {
          "nameUrl": "artifacts.html",
          "title": "Artifacts",
          "generation": "html"
        },
        {
          "nameUrl": "example-resources.html",
          "title": "Example Resources",
          "generation": "markdown"
        },
        {
          "nameUrl": "example-scenarios.html",
          "title": "Example Scenarios",
          "generation": "markdown"
        },
        {
          "nameUrl": "downloads.html",
          "title": "Useful Downloads",
          "generation": "html"
        },
        {
          "nameUrl": "changes.html",
          "title": "IG Change History",
          "generation": "html"
        }
      ]
    },
    "parameter": [
      {
        "code": "path-resource",
        "value": "input/capabilities"
      },
      {
        "code": "path-resource",
        "value": "input/examples"
      },
      {
        "code": "path-resource",
        "value": "input/extensions"
      },
      {
        "code": "path-resource",
        "value": "input/models"
      },
      {
        "code": "path-resource",
        "value": "input/operations"
      },
      {
        "code": "path-resource",
        "value": "input/profiles"
      },
      {
        "code": "path-resource",
        "value": "input/resources"
      },
      {
        "code": "path-resource",
        "value": "input/vocabulary"
      },
      {
        "code": "path-pages",
        "value": "template/config"
      },
      {
        "code": "path-pages",
        "value": "input/images"
      },
      {
        "code": "path-tx-cache",
        "value": "input-cache/txcache"
      }
    ]
  }
}